hex_json/__init__.py
hex_json/src.py
tests/__init__.py
tests/test_hex_json.py
hex_json-0.0.2.1.dist-info/LICENSE
hex_json-0.0.2.1.dist-info/METADATA
hex_json-0.0.2.1.dist-info/WHEEL
hex_json-0.0.2.1.dist-info/top_level.txt
hex_json-0.0.2.1.dist-info/RECORD
