Metadata-Version: 2.1
Name: hex-json
Version: 0.0.2.1
Summary: Convert [Python dictionary | ASCII JSON string] into hexadecimal string.
Home-page: https://github.com/Sobolev5/hex-json/
Author: Sobolev Andrey
Author-email: email.asobolev@gmail.com
License: UNKNOWN
Platform: UNKNOWN
Classifier: Programming Language :: Python :: 3
Classifier: License :: OSI Approved :: MIT License
Classifier: Operating System :: OS Independent
Requires-Python: >=3.8
License-File: LICENSE
Requires-Dist: orjson (>=3.8.6)
